geoagent/__init__.py
geoagent/catalogs/__init__.py
geoagent/catalogs/registry.py
geoagent/core/__init__.py
geoagent/core/agent.py
geoagent/core/analysis_agent.py
geoagent/core/data_agent.py
geoagent/core/llm.py
geoagent/core/models.py
geoagent/core/planner.py
geoagent/core/viz_agent.py
geoagent/core/tools/__init__.py
geoagent/core/tools/duckdb_tool.py
geoagent/core/tools/raster.py
geoagent/core/tools/stac.py
geoagent/core/tools/vector.py
geoagent/core/tools/viz.py
geoagent/ui/__init__.py
geoagent-0.1.0.dist-info/licenses/LICENSE
geoagent-0.1.0.dist-info/METADATA
geoagent-0.1.0.dist-info/WHEEL
geoagent-0.1.0.dist-info/entry_points.txt
geoagent-0.1.0.dist-info/top_level.txt
geoagent-0.1.0.dist-info/RECORD
