Metadata-Version: 2.4
Name: GeoAgent
Version: 0.1.0
Summary: An AI agent for geospatial data analysis and visualization
Author-email: Qiusheng Wu <giswqs@gmail.com>
License: MIT License
Project-URL: Homepage, https://github.com/opengeos/GeoAgent
Keywords: GeoAgent,geospatial,AI,agent,STAC,remote sensing,earth observation
Classifier: Intended Audience :: Developers
Classifier: Intended Audience :: Science/Research
Classifier: License :: OSI Approved :: MIT License
Classifier: Natural Language :: English
Classifier: Programming Language :: Python :: 3.10
Classifier: Programming Language :: Python :: 3.11
Classifier: Programming Language :: Python :: 3.12
Classifier: Programming Language :: Python :: 3.13
Requires-Python: >=3.10
License-File: LICENSE
Requires-Dist: langgraph>=0.2
Requires-Dist: langchain>=0.3
Requires-Dist: langchain-core>=0.3
Requires-Dist: langchain-openai>=0.2
Requires-Dist: leafmap>=0.43
Requires-Dist: pystac-client>=0.8
Requires-Dist: planetary-computer>=1.0
Requires-Dist: geopy>=2.4
Requires-Dist: pyproj>=3.6
Requires-Dist: xarray>=2024.1
Requires-Dist: rioxarray>=0.17
Requires-Dist: rasterio>=1.3
Requires-Dist: geopandas>=1.0
Requires-Dist: duckdb>=1.1
Requires-Dist: numpy>=1.26
Requires-Dist: pandas>=2.1
Requires-Dist: shapely>=2.0
Requires-Dist: pydantic>=2.0
Provides-Extra: llm
Requires-Dist: langchain-anthropic>=0.2; extra == "llm"
Requires-Dist: langchain-google-genai>=2.0; extra == "llm"
Provides-Extra: ollama
Requires-Dist: langchain-ollama>=0.2; extra == "ollama"
Provides-Extra: ui
Requires-Dist: streamlit>=1.38; extra == "ui"
Requires-Dist: solara>=1.35; extra == "ui"
Provides-Extra: all
Requires-Dist: GeoAgent[llm,ollama,ui]; extra == "all"
Provides-Extra: dev
Requires-Dist: pytest>=8.0; extra == "dev"
Requires-Dist: pytest-asyncio>=0.24; extra == "dev"
Requires-Dist: ruff>=0.7; extra == "dev"
Requires-Dist: pre-commit>=4.0; extra == "dev"
Dynamic: license-file
